<?xml version="1.0" encoding="utf-8" ?>
<dwsync>
<file name="fb.png" server="C:/AppServ/www/symbiot/" local="131455754854184027" remote="131455754850000000" Dst="2" />
<file name="gp.png" server="C:/AppServ/www/symbiot/" local="131455754951274937" remote="131455754950000000" Dst="2" />
<file name="ig.png" server="C:/AppServ/www/symbiot/" local="131455755108388361" remote="131455755100000000" Dst="2" />
<file name="in.png" server="C:/AppServ/www/symbiot/" local="131455754601397142" remote="131455754600000000" Dst="2" />
<file name="tw.png" server="C:/AppServ/www/symbiot/" local="131455755023850989" remote="131455755020000000" Dst="2" />
<file name="yt.png" server="C:/AppServ/www/symbiot/" local="131455755190830056" remote="131455755190000000" Dst="2" />
<file name="fb.png" server="ftp.symbiot.com.mx/httpdocs/" local="131455754854184027" remote="131455945200000000" Dst="2" />
<file name="gp.png" server="ftp.symbiot.com.mx/httpdocs/" local="131455754951274937" remote="131455945200000000" Dst="2" />
<file name="ig.png" server="ftp.symbiot.com.mx/httpdocs/" local="131455755108388361" remote="131455945200000000" Dst="2" />
<file name="in.png" server="ftp.symbiot.com.mx/httpdocs/" local="131455754601397142" remote="131455945200000000" Dst="2" />
<file name="tw.png" server="ftp.symbiot.com.mx/httpdocs/" local="131455755023850989" remote="131455945200000000" Dst="2" />
<file name="yt.png" server="ftp.symbiot.com.mx/httpdocs/" local="131455755190830056" remote="131455945200000000" Dst="2" />
<file name="symbiosis-concept-art-wallpaper.jpg" server="ftp.symbiot.com.mx/httpdocs/" local="131456420969484452" remote="131456605800000000" Dst="2" />
<file name="symbiosis-concept-art-wallpaper.jpg" server="C:/AppServ/www/symbiot/" local="131456420969484452" remote="131456420960000000" Dst="2" />
<file name="s1-min.png" server="C:/AppServ/www/symbiot/" local="131460830309757138" remote="131460830300000000" Dst="2" />
<file name="s2-min.jpg" server="C:/AppServ/www/symbiot/" local="131460830541917479" remote="131460830540000000" Dst="2" />
<file name="s2-min.png" server="C:/AppServ/www/symbiot/" local="131460830585150006" remote="131460830580000000" Dst="2" />
<file name="s3-min.png" server="C:/AppServ/www/symbiot/" local="131460831398360373" remote="131460831390000000" Dst="2" />
<file name="StockSnap_OA19XEAJML.jpg" server="C:/AppServ/www/symbiot/" local="131457328489996169" remote="131457328480000000" Dst="2" />
<file name="pic-battery.svg" server="C:/AppServ/www/symbiot/" local="131457400841718150" remote="131457400840000000" Dst="2" />
<file name="pic-comp.svg" server="C:/AppServ/www/symbiot/" local="131457400927783267" remote="131457400920000000" Dst="2" />
<file name="pic-pig.svg" server="C:/AppServ/www/symbiot/" local="131457400901658174" remote="131457400900000000" Dst="2" />
<file name="wom.png" server="C:/AppServ/www/symbiot/" local="131460831272545614" remote="131460831270000000" Dst="2" />
<file name="symbiot_logo_mini_horizontal.png" server="C:/AppServ/www/symbiot/" local="131457404215707607" remote="131457404210000000" Dst="2" />
<file name="pic-battery.svg" server="ftp.symbiot.com.mx/httpdocs/" local="131457400841718150" remote="131457774000000000" Dst="2" />
<file name="pic-comp.svg" server="ftp.symbiot.com.mx/httpdocs/" local="131457400927783267" remote="131457774000000000" Dst="2" />
<file name="pic-pig.svg" server="ftp.symbiot.com.mx/httpdocs/" local="131457400901658174" remote="131457774000000000" Dst="2" />
<file name="s1-min.png" server="ftp.symbiot.com.mx/httpdocs/" local="131460830309757138" remote="131461015800000000" Dst="2" />
<file name="s2-min.jpg" server="ftp.symbiot.com.mx/httpdocs/" local="131460830541917479" remote="131461015800000000" Dst="2" />
<file name="s2-min.png" server="ftp.symbiot.com.mx/httpdocs/" local="131460830585150006" remote="131461015800000000" Dst="2" />
<file name="s3-min.png" server="ftp.symbiot.com.mx/httpdocs/" local="131460831398360373" remote="131461016400000000" Dst="2" />
<file name="StockSnap_OA19XEAJML.jpg" server="ftp.symbiot.com.mx/httpdocs/" local="131457328489996169" remote="131457774600000000" Dst="2" />
<file name="symbiot_logo_mini_horizontal.png" server="ftp.symbiot.com.mx/httpdocs/" local="131457404215707607" remote="131457774600000000" Dst="2" />
<file name="wom.png" server="ftp.symbiot.com.mx/httpdocs/" local="131460831272545614" remote="131461017000000000" Dst="2" />
<file name="automotive-918614_1280-449x300.png" server="ftp.symbiot.com.mx/httpdocs/" local="131460827582252081" remote="131461014600000000" Dst="2" />
<file name="board_1280-450x300.png" server="ftp.symbiot.com.mx/httpdocs/" local="131460828050684356" remote="131461015200000000" Dst="2" />
<file name="code-983967_640.png" server="ftp.symbiot.com.mx/httpdocs/" local="131534611039887378" remote="131534794800000000" Dst="2" />
<file name="hard-disk-678834_1280.png" server="ftp.symbiot.com.mx/httpdocs/" local="131460828673877905" remote="131461015200000000" Dst="2" />
<file name="hardware-659352_1280-450x300.png" server="ftp.symbiot.com.mx/httpdocs/" local="131534611807345951" remote="131534794800000000" Dst="2" />
<file name="laptop-425818_1280-450x300.png" server="ftp.symbiot.com.mx/httpdocs/" local="131460829401485251" remote="131461015800000000" Dst="2" />
<file name="network-919047_1280-450x300.png" server="ftp.symbiot.com.mx/httpdocs/" local="131460829842669452" remote="131461015800000000" Dst="2" />
<file name="azure.png" server="ftp.symbiot.com.mx/httpdocs/" local="131457694143855458" remote="131457874800000000" Dst="2" />
<file name="circuit-board-355157_640.png" server="ftp.symbiot.com.mx/httpdocs/" local="131460828268634773" remote="131461015200000000" Dst="2" />
<file name="keyboard-354565_1280-450x300.png" server="ftp.symbiot.com.mx/httpdocs/" local="131460829158487124" remote="131461015200000000" Dst="2" />
<file name="smart-city-837156_640.png" server="ftp.symbiot.com.mx/httpdocs/" local="131460830900239381" remote="131461016400000000" Dst="2" />
<file name="automotive-918614_1280-449x300.png" server="C:/AppServ/www/symbiot/" local="131460827582252081" remote="131460827580000000" Dst="2" />
<file name="azure.png" server="C:/AppServ/www/symbiot/" local="131457694143855458" remote="131457694140000000" Dst="2" />
<file name="board_1280-450x300.png" server="C:/AppServ/www/symbiot/" local="131460828050684356" remote="131460828050000000" Dst="2" />
<file name="circuit-board-355157_640.png" server="C:/AppServ/www/symbiot/" local="131460828268634773" remote="131460828260000000" Dst="2" />
<file name="code-983967_640.png" server="C:/AppServ/www/symbiot/" local="131460828446148113" remote="131460828440000000" Dst="2" />
<file name="hard-disk-678834_1280.png" server="C:/AppServ/www/symbiot/" local="131460828673877905" remote="131460828670000000" Dst="2" />
<file name="hardware-659352_1280-450x300.png" server="C:/AppServ/www/symbiot/" local="131460828880186616" remote="131460828880000000" Dst="2" />
<file name="keyboard-354565_1280-450x300.png" server="C:/AppServ/www/symbiot/" local="131460829158487124" remote="131460829150000000" Dst="2" />
<file name="laptop-425818_1280-450x300.png" server="C:/AppServ/www/symbiot/" local="131460829401485251" remote="131460829400000000" Dst="2" />
<file name="network-919047_1280-450x300.png" server="C:/AppServ/www/symbiot/" local="131460829842669452" remote="131460829840000000" Dst="2" />
<file name="smart-city-837156_640.png" server="C:/AppServ/www/symbiot/" local="131460830900239381" remote="131460830900000000" Dst="2" />
<file name="mac.png" server="ftp.symbiot.com.mx/httpdocs/" local="131460829600501393" remote="131461015800000000" Dst="2" />
<file name="mac.png" server="C:/AppServ/www/symbiot/" local="131460829600501393" remote="131460829600000000" Dst="2" />
<file name="s3-min.jpg" server="ftp.symbiot.com.mx/httpdocs/" local="131460831364883119" remote="131461016400000000" Dst="2" />
<file name="s3-min.jpg" server="C:/AppServ/www/symbiot/" local="131460831364883119" remote="131460831360000000" Dst="2" />
<file name="20170223232006-GettyImages-557475765.jpeg" server="C:/AppServ/www/symbiot/" local="131460821087637076" remote="131460821080000000" Dst="2" />
<file name="smedia-min.png" server="C:/AppServ/www/symbiot/" local="131460822149761089" remote="131460822140000000" Dst="2" />
<file name="social-media-763731_1280.jpg" server="C:/AppServ/www/symbiot/" local="131460816297794339" remote="131460816290000000" Dst="2" />
<file name="20170223232006-GettyImages-557475765.jpeg" server="ftp.symbiot.com.mx/httpdocs/" local="131460821087637076" remote="131461004400000000" Dst="2" />
<file name="smedia-min.png" server="ftp.symbiot.com.mx/httpdocs/" local="131460822149761089" remote="131461009800000000" Dst="2" />
<file name="social-media-763731_1280.jpg" server="ftp.symbiot.com.mx/httpdocs/" local="131460816297794339" remote="131461009800000000" Dst="2" />
<file name="automotive-918614_1280-449x300.jpg" server="ftp.symbiot.com.mx/httpdocs/" local="131460827512540294" remote="131461014600000000" Dst="2" />
<file name="board_1280-450x300.jpg" server="ftp.symbiot.com.mx/httpdocs/" local="131460827989802805" remote="131461014600000000" Dst="2" />
<file name="circuit-board-355157_640.jpg" server="ftp.symbiot.com.mx/httpdocs/" local="131460828234781633" remote="131461015200000000" Dst="2" />
<file name="code-983967_640.jpg" server="ftp.symbiot.com.mx/httpdocs/" local="131534606139503960" remote="131534787600000000" Dst="2" />
<file name="hard-disk-678834_1280.jpg" server="ftp.symbiot.com.mx/httpdocs/" local="131460828634439572" remote="131461015200000000" Dst="2" />
<file name="hardware-659352_1280-450x300.jpg" server="ftp.symbiot.com.mx/httpdocs/" local="131534611764415359" remote="131534794800000000" Dst="2" />
<file name="keyboard-354565_1280-450x300.jpg" server="ftp.symbiot.com.mx/httpdocs/" local="131460829136086388" remote="131461015200000000" Dst="2" />
<file name="laptop-425818_1280-450x300.jpg" server="ftp.symbiot.com.mx/httpdocs/" local="131460829372344617" remote="131461015200000000" Dst="2" />
<file name="mac.jpg" server="ftp.symbiot.com.mx/httpdocs/" local="131460829574013802" remote="131461015800000000" Dst="2" />
<file name="network-919047_1280-450x300.jpg" server="ftp.symbiot.com.mx/httpdocs/" local="131460829814470743" remote="131461015800000000" Dst="2" />
<file name="s1-min.jpg" server="ftp.symbiot.com.mx/httpdocs/" local="131460830274254526" remote="131461015800000000" Dst="2" />
<file name="smart-city-837156_640.jpg" server="ftp.symbiot.com.mx/httpdocs/" local="131460830874393358" remote="131461016400000000" Dst="2" />
<file name="smedia-min.jpg" server="ftp.symbiot.com.mx/httpdocs/" local="131460827668186646" remote="131461016400000000" Dst="2" />
<file name="wom.jpg" server="ftp.symbiot.com.mx/httpdocs/" local="131460831243950534" remote="131461016400000000" Dst="2" />
<file name="automotive-918614_1280-449x300.jpg" server="C:/AppServ/www/symbiot/" local="131460827512540294" remote="131460827510000000" Dst="2" />
<file name="board_1280-450x300.jpg" server="C:/AppServ/www/symbiot/" local="131460827989802805" remote="131460827980000000" Dst="2" />
<file name="circuit-board-355157_640.jpg" server="C:/AppServ/www/symbiot/" local="131460828234781633" remote="131460828230000000" Dst="2" />
<file name="code-983967_640.jpg" server="C:/AppServ/www/symbiot/" local="131460828412905049" remote="131460828410000000" Dst="2" />
<file name="hard-disk-678834_1280.jpg" server="C:/AppServ/www/symbiot/" local="131460828634439572" remote="131460828630000000" Dst="2" />
<file name="hardware-659352_1280-450x300.jpg" server="C:/AppServ/www/symbiot/" local="131460828853278891" remote="131460828850000000" Dst="2" />
<file name="keyboard-354565_1280-450x300.jpg" server="C:/AppServ/www/symbiot/" local="131460829136086388" remote="131460829130000000" Dst="2" />
<file name="laptop-425818_1280-450x300.jpg" server="C:/AppServ/www/symbiot/" local="131460829372344617" remote="131460829370000000" Dst="2" />
<file name="mac.jpg" server="C:/AppServ/www/symbiot/" local="131460829574013802" remote="131460829570000000" Dst="2" />
<file name="network-919047_1280-450x300.jpg" server="C:/AppServ/www/symbiot/" local="131460829814470743" remote="131460829810000000" Dst="2" />
<file name="s1-min.jpg" server="C:/AppServ/www/symbiot/" local="131460830274254526" remote="131460830270000000" Dst="2" />
<file name="smart-city-837156_640.jpg" server="C:/AppServ/www/symbiot/" local="131460830874393358" remote="131460830870000000" Dst="2" />
<file name="smedia-min.jpg" server="C:/AppServ/www/symbiot/" local="131460827668186646" remote="131460827660000000" Dst="2" />
<file name="wom.jpg" server="C:/AppServ/www/symbiot/" local="131460831243950534" remote="131460831240000000" Dst="2" />
<file name="apps-size-page.jpg" server="ftp.symbiot.com.mx/httpdocs/" local="131461743141207499" remote="131461923600000000" Dst="2" />
<file name="apps.jpg" server="ftp.symbiot.com.mx/httpdocs/" local="131461740646162794" remote="131461923600000000" Dst="2" />
<file name="apps.png" server="ftp.symbiot.com.mx/httpdocs/" local="131461743200338409" remote="131461923600000000" Dst="2" />
<file name="mobile-app-dev.jpg" server="ftp.symbiot.com.mx/httpdocs/" local="131461740813092191" remote="131461923600000000" Dst="2" />
<file name="541201_10150879123504547_785223423_n.jpg" server="C:/AppServ/www/symbiot/" local="131461779193986126" remote="131461779190000000" Dst="2" />
<file name="apps-size-page.jpg" server="C:/AppServ/www/symbiot/" local="131461743141207499" remote="131461743140000000" Dst="2" />
<file name="apps.jpg" server="C:/AppServ/www/symbiot/" local="131461740646162794" remote="131461740640000000" Dst="2" />
<file name="apps.png" server="C:/AppServ/www/symbiot/" local="131461743200338409" remote="131461743200000000" Dst="2" />
<file name="mobile-app-dev.jpg" server="C:/AppServ/www/symbiot/" local="131461740813092191" remote="131461740810000000" Dst="2" />
<file name="541201_10150879123504547_785223423_n.jpg" server="ftp.symbiot.com.mx/httpdocs/" local="131461779193986126" remote="131464764000000000" Dst="2" />
<file name="bg_symbiot2.jpg" server="ftp.symbiot.com.mx/httpdocs/" local="131533790587852047" remote="131533987200000000" Dst="2" />
<file name="symbiot.gif" server="ftp.symbiot.com.mx/httpdocs/" local="131537200640486204" remote="131537448600000000" Dst="2" />
</dwsync>